MANIFEST.in
README.rst
distribute_setup.py
setup.py
restq/__init__.py
restq/__main__.py
restq/cli.py
restq/client.py
restq/config.py
restq/realms.py
restq/version.py
restq/webapp.py
restq.egg-info/PKG-INFO
restq.egg-info/SOURCES.txt
restq.egg-info/dependency_links.txt
restq.egg-info/entry_points.txt
restq.egg-info/not-zip-safe
restq.egg-info/requires.txt
restq.egg-info/top_level.txt
tests/__init__.py
tests/load_hash_test.py
tests/test_api.py
tests/test_client.py
tests/test_mem.py
tests/test_realms.py