Metadata-Version: 1.1
Name: restq
Version: 0.1.2
Summary: All-in-memory job queue with RESTful interface.
Home-page: https://github.com/provoke-vagueness/restq
Author: Michael Dorman and Stephen Tonkin
Author-email: mjdorma@gmail.com sptonkin@outlook.com
License: Apache Software Licence
Platform: cygwin
Platform: win
Platform: linux
Classifier: Development Status :: 2 - Pre-Alpha
Classifier: Intended Audience :: Other Audience
Classifier: License :: OSI Approved :: Apache Software License
Classifier: Operating System :: Microsoft :: Windows
Classifier: Operating System :: POSIX :: Linux
Classifier: Programming Language :: Python
Classifier: Programming Language :: Python :: 2.6
Classifier: Programming Language :: Python :: 2.7
Classifier: Programming Language :: Python :: 3
Classifier: Programming Language :: Python :: 3.2
Classifier: Programming Language :: Python :: 3.3
Classifier: Programming Language :: Python :: Implementation :: CPython
Classifier: Topic :: Security
Classifier: Topic :: System :: Monitoring
